{
   "Groups":[
      {
         "Name":"Main",
         "DisplayName":"Options",
         "Elements":
         [
            {
               "Name":"IncludeDir1",
               "DisplayName":"Blaze Support",
               "Description":[
                  "Choose if you want Blaze support enabled or disabled. Press the Y button to use her. Works even in modded stages. Triggers Blaze's intro all the time.",
               ],
               "Type":"SupportType",
               "MinValue":null,
               "MaxValue":null,
               "DefaultValue":"blaze_support"
            },
            {
               "Name":"IncludeDir2",
               "DisplayName":"Physics",
               "Description":[
			      "Choose if you want custom physics or not."
               ],
               "Type":"PhysicsType",
               "MinValue":null,
               "MaxValue":null,
               "DefaultValue":"character_physics"
            },
			{
               "Name":"IncludeDir3",
               "DisplayName":"HUD",
               "Description":[
			      "Choose what type of HUD you want."
               ],
               "Type":"HUDType",
               "MinValue":null,
               "MaxValue":null,
               "DefaultValue":"sth_hud"
            },
         ]
      }
   ],
   "Enums":{
      "SupportType":[
         {
            "DisplayName":"No",
            "Value":"common_assets",
            "Description":[
               "Blaze support is disabled.",
            ]
         },
         {
            "DisplayName":"Yes",
            "Value":"blaze_support",
            "Description":[
               "Blaze support is enabled.",
            ]
         }
      ],
	  "PhysicsType":[
         {
            "DisplayName":"No",
            "Value":"common_assets",
            "Description":[
               "Physics are disabled.",
            ]
         },
         {
            "DisplayName":"Yes",
            "Value":"character_physics",
            "Description":[
               "Physics are enabled as followed:",
			   "-Disabled startup boost gauge usage",
			   "-Enabled hovering",
			   "-Spin ball jump is disabled",
			   "-Boost on water and in the air uses the same amount of energy as on the ground",
			   "-Physics are not changed in Infinite Rival and Egg Dragoon fights",
			   "-Physics work if custom stages don't have their own custom physics",
            ]
         },
		 {
            "DisplayName":"brianuuuSonic's physics",
            "Value":"cursed_physics",
            "Description":[
               "You're an absolute madman to use this one.",
            ]
         }
      ],
	  "HUDType":[
         {
            "DisplayName":"Original HUD",
            "Value":"original_hud",
            "Description":[
               "Recolored to match Silver. Made by STRIKE.",
            ]
         },
         {
            "DisplayName":"Sonic 06 HUD",
            "Value":"sth_hud",
            "Description":[
               "Sonic The Hedgehog 2006 HUD. Made by brianuuuSonic.",
            ]
         }
      ]
   },
   "IniFile":"mod.ini"
}